src/__init__.py
src/property.py
src/apify/__init__.py
src/apify/skip_trace/__init__.py
src/apify/skip_trace/owner_data.py
src/apify/skip_trace/skip_trace_actor.py
src/apify/zillow_scrapers/__init__.py
src/apify/zillow_scrapers/common/__init__.py
src/apify/zillow_scrapers/common/actor.py
src/apify/zillow_scrapers/common/client.py
src/apify/zillow_scrapers/common/config.py
src/apify/zillow_scrapers/common/contingency_status_extractor.py
src/apify/zillow_scrapers/zillow_detail_scraper/__init__.py
src/apify/zillow_scrapers/zillow_detail_scraper/on_the_fly_runner.py
src/apify/zillow_scrapers/zillow_detail_scraper/scraper.py
src/apify/zillow_scrapers/zillow_search_scraper/__init__.py
src/apify/zillow_scrapers/zillow_search_scraper/scraper.py
src/common/__init__.py
src/common/addresses_utils/__init__.py
src/common/addresses_utils/address_maniplator.py
src/common/addresses_utils/city_normalizer.py
src/common/geo_utils/__init__.py
src/common/geo_utils/distance_calculator.py
src/common/geo_utils/geo_encoder.py
src/common/geo_utils/zip_code_finder.py
src/common/utils/__init__.py
src/common/utils/logger.py
src/comps_extractor/__init__.py
src/comps_extractor/comps_generator.py
src/comps_extractor/utils/__init__.py
src/comps_extractor/utils/bounding_box_calculator.py
src/comps_extractor/utils/coordinates.py
src/flows/__init__.py
src/flows/flows_meta.py
src/flows/common/__init__.py
src/flows/common/contingent_status.py
src/flows/common/leads_filters/__init__.py
src/flows/common/leads_filters/abstract_filter.py
src/flows/common/leads_filters/ap_filter.py
src/flows/common/leads_filters/bedrooms_filter.py
src/flows/common/leads_filters/desired_neighborhoods_filter.py
src/flows/common/leads_filters/filters.py
src/flows/common/leads_filters/property_sqft_filter.py
src/flows/leads_cleaner_flow/__init__.py
src/flows/leads_cleaner_flow/contingent_status_handlers.py
src/flows/leads_cleaner_flow/flow.py
src/flows/leads_cleaner_flow/get_leads_properties.py
ihopesproperties-2.0.2.dist-info/METADATA
ihopesproperties-2.0.2.dist-info/WHEEL
ihopesproperties-2.0.2.dist-info/top_level.txt
ihopesproperties-2.0.2.dist-info/RECORD
