Metadata-Version: 2.4
Name: IHopesProperties
Version: 2.0.2
Summary: Leads flow of IHopesProperties
Author: Ori Peri
Author-email: 25to40@gmail.com
Dynamic: author
Dynamic: author-email
Dynamic: summary
